data_wrangling_components/__init__.py
data_wrangling_components/engine/__init__.py
data_wrangling_components/engine/pandas/__init__.py
data_wrangling_components/engine/pandas/aggregate_mapping.py
data_wrangling_components/engine/pandas/filter_df.py
data_wrangling_components/engine/verbs/__init__.py
data_wrangling_components/engine/verbs/aggregate.py
data_wrangling_components/engine/verbs/bin.py
data_wrangling_components/engine/verbs/binarize.py
data_wrangling_components/engine/verbs/boolean.py
data_wrangling_components/engine/verbs/concat.py
data_wrangling_components/engine/verbs/convert.py
data_wrangling_components/engine/verbs/dedupe.py
data_wrangling_components/engine/verbs/derive.py
data_wrangling_components/engine/verbs/difference.py
data_wrangling_components/engine/verbs/erase.py
data_wrangling_components/engine/verbs/fetch.py
data_wrangling_components/engine/verbs/fill.py
data_wrangling_components/engine/verbs/filter.py
data_wrangling_components/engine/verbs/fold.py
data_wrangling_components/engine/verbs/groupby.py
data_wrangling_components/engine/verbs/impute.py
data_wrangling_components/engine/verbs/intersect.py
data_wrangling_components/engine/verbs/join.py
data_wrangling_components/engine/verbs/lookup.py
data_wrangling_components/engine/verbs/merge.py
data_wrangling_components/engine/verbs/onehot.py
data_wrangling_components/engine/verbs/orderby.py
data_wrangling_components/engine/verbs/pivot.py
data_wrangling_components/engine/verbs/recode.py
data_wrangling_components/engine/verbs/rename.py
data_wrangling_components/engine/verbs/rollup.py
data_wrangling_components/engine/verbs/sample.py
data_wrangling_components/engine/verbs/select.py
data_wrangling_components/engine/verbs/spread.py
data_wrangling_components/engine/verbs/unfold.py
data_wrangling_components/engine/verbs/ungroup.py
data_wrangling_components/engine/verbs/union.py
data_wrangling_components/engine/verbs/unorder.py
data_wrangling_components/engine/verbs/unroll.py
data_wrangling_components-0.0.6.dist-info/WHEEL
data_wrangling_components-0.0.6.dist-info/METADATA
data_wrangling_components-0.0.6.dist-info/RECORD
