Metadata-Version: 2.1
Name: data-wrangling-components
Version: 0.0.6
Summary: This project provides a collection of utilities for doing lightweight data wrangling.
License: MIT
Author: Nathan Evans
Author-email: naevans@microsoft.com
Requires-Python: >=3.8,<3.10
Classifier: License :: OSI Approved :: MIT License
Classifier: Programming Language :: Python :: 3
Classifier: Programming Language :: Python :: 3.8
Classifier: Programming Language :: Python :: 3.9
Requires-Dist: black (>=22.3.0,<23.0.0)
Requires-Dist: jsonschema (>=4.5.1,<5.0.0)
Requires-Dist: pandas (>=1.4.1,<2.0.0)
